{
  "posts": [
    {
      "id": "323396ccd4af8032929dcb50eb5d32e6",
      "title": "Nytt år - Ny hemsida!",
      "summary": "Testar den nya bloggen!",
      "date": "2026-03-14",
      "cover": "data/img/blog_f14496ade10c.jpg",
      "content": [
        {
          "type": "paragraph",
          "text": "Testtext… bla bla bla. Testtext… bla bla bla. Testtext… bla bla bla. Testtext… bla bla bla. Testtext… bla bla bla. Testtext… bla bla bla. Testtext… bla bla bla. Testtext… bla bla bla. Testtext… bla bla bla. Testtext… bla bla bla. Testtext… bla bla bla. Testtext… bla bla bla. Testtext… bla bla bla. Testtext… bla bla bla. Testtext… bla bla bla. Testtext… bla bla bla. Testtext… bla bla bla. Testtext… bla bla bla. Testtext… bla bla bla. Testtext… bla bla bla. Testtext… bla bla bla. Testtext… bla bla bla. Testtext… bla bla bla. Testtext… bla bla bla. Testtext… bla bla bla. Testtext… bla bla bla. "
        },
        {
          "type": "image",
          "url": "data/img/blog_1717ba229454.png"
        }
      ]
    }
  ],
  "updated": "2026-03-14T20:46:50.926141+00:00"
}