{
  "posts": [
    {
      "id": "323396ccd4af8032929dcb50eb5d32e6",
      "title": "Nytt år - Ny hemsida!",
      "summary": "Testar den nya bloggen!",
      "date": "2026-03-14",
      "cover": "data/img/blog_8a078d257ad1.jpg",
      "content": [
        {
          "type": "paragraph",
          "text": "Testtext… bla bla bla. Testtext… bla bla bla. Testtext… bla bla bla. Testtext… bla bla bla. Testtext… bla bla bla. Testtext… bla bla bla. Testtext… bla bla bla. Testtext… bla bla bla. Testtext… bla bla bla. Testtext… bla bla bla. Testtext… bla bla bla. Testtext… bla bla bla. Testtext… bla bla bla. Testtext… bla bla bla. Testtext… bla bla bla. Testtext… bla bla bla. Testtext… bla bla bla. Testtext… bla bla bla. Testtext… bla bla bla. Testtext… bla bla bla. Testtext… bla bla bla. Testtext… bla bla bla. Testtext… bla bla bla. Testtext… bla bla bla. Testtext… bla bla bla. Testtext… bla bla bla. "
        },
        {
          "type": "image",
          "url": "data/img/blog_45da196da1c4.png"
        }
      ]
    },
    {
      "id": "323396ccd4af803bbf43cd838493c86d",
      "title": "Nytt år - Ny hemsida! (1)",
      "summary": "Testar den nya bloggen!",
      "date": "2026-03-14",
      "cover": "data/img/blog_8a078d257ad1.jpg",
      "content": [
        {
          "type": "paragraph",
          "text": "Testtext… bla bla bla. Testtext… bla bla bla. Testtext… bla bla bla. Testtext… bla bla bla. Testtext… bla bla bla. Testtext… bla bla bla. Testtext… bla bla bla. Testtext… bla bla bla. Testtext… bla bla bla. Testtext… bla bla bla. Testtext… bla bla bla. Testtext… bla bla bla. Testtext… bla bla bla. Testtext… bla bla bla. Testtext… bla bla bla. Testtext… bla bla bla. Testtext… bla bla bla. Testtext… bla bla bla. Testtext… bla bla bla. Testtext… bla bla bla. Testtext… bla bla bla. Testtext… bla bla bla. Testtext… bla bla bla. Testtext… bla bla bla. Testtext… bla bla bla. Testtext… bla bla bla. "
        },
        {
          "type": "image",
          "url": "data/img/blog_3b7a05d3d1d2.png"
        }
      ]
    },
    {
      "id": "323396ccd4af80a6a1a9c5fb99fe1d9d",
      "title": "Nytt år - Ny hemsida! (3)",
      "summary": "Testar den nya bloggen!",
      "date": "2026-03-14",
      "cover": "data/img/blog_8a078d257ad1.jpg",
      "content": [
        {
          "type": "paragraph",
          "text": "Testtext… bla bla bla. Testtext… bla bla bla. Testtext… bla bla bla. Testtext… bla bla bla. Testtext… bla bla bla. Testtext… bla bla bla. Testtext… bla bla bla. Testtext… bla bla bla. Testtext… bla bla bla. Testtext… bla bla bla. Testtext… bla bla bla. Testtext… bla bla bla. Testtext… bla bla bla. Testtext… bla bla bla. Testtext… bla bla bla. Testtext… bla bla bla. Testtext… bla bla bla. Testtext… bla bla bla. Testtext… bla bla bla. Testtext… bla bla bla. Testtext… bla bla bla. Testtext… bla bla bla. Testtext… bla bla bla. Testtext… bla bla bla. Testtext… bla bla bla. Testtext… bla bla bla. "
        },
        {
          "type": "image",
          "url": "data/img/blog_b9fa39417f96.png"
        }
      ]
    },
    {
      "id": "323396ccd4af80c7baa2db7b9a08126d",
      "title": "Nytt år - Ny hemsida! (2)",
      "summary": "Testar den nya bloggen!",
      "date": "2026-03-14",
      "cover": "data/img/blog_8a078d257ad1.jpg",
      "content": [
        {
          "type": "paragraph",
          "text": "Testtext… bla bla bla. Testtext… bla bla bla. Testtext… bla bla bla. Testtext… bla bla bla. Testtext… bla bla bla. Testtext… bla bla bla. Testtext… bla bla bla. Testtext… bla bla bla. Testtext… bla bla bla. Testtext… bla bla bla. Testtext… bla bla bla. Testtext… bla bla bla. Testtext… bla bla bla. Testtext… bla bla bla. Testtext… bla bla bla. Testtext… bla bla bla. Testtext… bla bla bla. Testtext… bla bla bla. Testtext… bla bla bla. Testtext… bla bla bla. Testtext… bla bla bla. Testtext… bla bla bla. Testtext… bla bla bla. Testtext… bla bla bla. Testtext… bla bla bla. Testtext… bla bla bla. "
        },
        {
          "type": "image",
          "url": "data/img/blog_a2dd58ec0b7a.png"
        }
      ]
    },
    {
      "id": "323396ccd4af80cfadf5c2f5b757e370",
      "title": "Nytt år - Ny hemsida! (1)",
      "summary": "Testar den nya bloggen!",
      "date": "2026-03-14",
      "cover": "data/img/blog_8a078d257ad1.jpg",
      "content": [
        {
          "type": "paragraph",
          "text": "Testtext… bla bla bla. Testtext… bla bla bla. Testtext… bla bla bla. Testtext… bla bla bla. Testtext… bla bla bla. Testtext… bla bla bla. Testtext… bla bla bla. Testtext… bla bla bla. Testtext… bla bla bla. Testtext… bla bla bla. Testtext… bla bla bla. Testtext… bla bla bla. Testtext… bla bla bla. Testtext… bla bla bla. Testtext… bla bla bla. Testtext… bla bla bla. Testtext… bla bla bla. Testtext… bla bla bla. Testtext… bla bla bla. Testtext… bla bla bla. Testtext… bla bla bla. Testtext… bla bla bla. Testtext… bla bla bla. Testtext… bla bla bla. Testtext… bla bla bla. Testtext… bla bla bla. "
        },
        {
          "type": "image",
          "url": "data/img/blog_064be4ec29d8.png"
        }
      ]
    },
    {
      "id": "323396ccd4af80f18b84c21761960e5e",
      "title": "Nytt år - Ny hemsida! (2)",
      "summary": "Testar den nya bloggen!",
      "date": "2026-03-14",
      "cover": "data/img/blog_8a078d257ad1.jpg",
      "content": [
        {
          "type": "paragraph",
          "text": "Testtext… bla bla bla. Testtext… bla bla bla. Testtext… bla bla bla. Testtext… bla bla bla. Testtext… bla bla bla. Testtext… bla bla bla. Testtext… bla bla bla. Testtext… bla bla bla. Testtext… bla bla bla. Testtext… bla bla bla. Testtext… bla bla bla. Testtext… bla bla bla. Testtext… bla bla bla. Testtext… bla bla bla. Testtext… bla bla bla. Testtext… bla bla bla. Testtext… bla bla bla. Testtext… bla bla bla. Testtext… bla bla bla. Testtext… bla bla bla. Testtext… bla bla bla. Testtext… bla bla bla. Testtext… bla bla bla. Testtext… bla bla bla. Testtext… bla bla bla. Testtext… bla bla bla. "
        },
        {
          "type": "image",
          "url": "data/img/blog_62a006a6f745.png"
        }
      ]
    }
  ],
  "updated": "2026-03-14T21:29:00.374307+00:00"
}